radware/sdk/__init__.py
radware/sdk/api.py
radware/sdk/beans_common.py
radware/sdk/common.py
radware/sdk/configurator.py
radware/sdk/device.py
radware/sdk/exceptions.py
radware/sdk/management.py
radware/sdk/rest_driver.py
radware_sdk_common-0.4b32.data/data/sdk_requirements.txt
radware_sdk_common-0.4b32.dist-info/LICENSE
radware_sdk_common-0.4b32.dist-info/METADATA
radware_sdk_common-0.4b32.dist-info/WHEEL
radware_sdk_common-0.4b32.dist-info/top_level.txt
radware_sdk_common-0.4b32.dist-info/RECORD
