Metadata-Version: 2.1
Name: radware-sdk-common
Version: 0.4b32
Summary: Python Radware SDK
Home-page: https://pypi.python.org/pypi/radware-sdk-common
Author: Leon Meguira
Author-email: leonm@radware.com
License: Apache 2.0
Keywords: radware,sdk,api,configurators,beans
Platform: UNKNOWN
Classifier: Development Status :: 4 - Beta
Classifier: License :: OSI Approved :: Apache Software License
Classifier: Operating System :: OS Independent
Classifier: Programming Language :: Python :: 3.6
Classifier: Programming Language :: Python :: 3.7
Classifier: Programming Language :: Python :: 3.8
Classifier: Intended Audience :: System Administrators
Classifier: Intended Audience :: Developers
Requires-Python: ~=3.6
Requires-Dist: typing-inspect (>0.3)
Requires-Dist: urllib3 (>=1.23)
